{
  "version": "1.0.0",
  "rss": "<LINK TO RSS FEED>",
  "discord": {
    "clientId": "<FILL IN OR REMOVE DISCORD OBJECT>",
    "smallImageText": "<FILL IN OR REMOVE DISCORD OBJECT>",
    "smallImageKey": "<FILL IN OR REMOVE DISCORD OBJECT>"
  },
  "servers": [
    {
      "id": "byeol2ddan-1.21.4",
      "name": "별 이 딴 서버가 다 있어!?",
      "description": "Minecraft 1.21.4 (Fabric v0.16.14)",
      "icon": "https://github.com/mchdistro/byeol2ddan/raw/main/server-icon.png",
      "version": "1.0.0",
      "address": "mc.gotiger.dev:25551",
      "minecraftVersion": "1.21.4",
      "discord": {
        "shortId": "<FILL IN OR REMOVE DISCORD OBJECT>",
        "largeImageText": "<FILL IN OR REMOVE DISCORD OBJECT>",
        "largeImageKey": "<FILL IN OR REMOVE DISCORD OBJECT>"
      },
      "mainServer": true,
      "autoconnect": false,
      "javaOptions": {
        "supported": "21",
        "suggestedMajor": 21,
        "platformOptions": [
          {
            "platform": "win32",
            "architecture": "x64",
            "distribution": "TEMURIN"
          }
        ],
        "ram": {
          "minimum": 4096,
          "recommended": 8192
        }
      },
      "modules": [
        {
          "id": "net.fabricmc:fabric-loader:0.16.14",
          "name": "Fabric (fabric-loader)",
          "type": "Fabric",
          "artifact": {
            "size": 1416842,
            "MD5": "e041ec21fad8f4dbd2ba7e73c25900d1",
            "url": "https://github.com/mchdistro/byeol2ddan/raw/main/repo/lib/net/fabricmc/fabric-loader/0.16.14/fabric-loader-0.16.14.jar"
          },
          "subModules": [
            {
              "id": "1.21.4-fabric-0.16.14",
              "name": "Fabric (version.json)",
              "type": "VersionManifest",
              "artifact": {
                "size": 2849,
                "MD5": "bf2443e4cf7609a947cf156d8cf86d7b",
                "url": "https://github.com/mchdistro/byeol2ddan/raw/main/repo/versions/1.21.4-fabric-0.16.14/1.21.4-fabric-0.16.14.json"
              }
            },
            {
              "id": "org.ow2.asm:asm:9.8",
              "name": "Fabric (asm)",
              "type": "Library",
              "artifact": {
                "size": 126113,
                "MD5": "f5adf3bfc54fb3d2cd8e3a1f275084bc",
                "url": "https://github.com/mchdistro/byeol2ddan/raw/main/repo/lib/org/ow2/asm/asm/9.8/asm-9.8.jar"
              }
            },
            {
              "id": "org.ow2.asm:asm-analysis:9.8",
              "name": "Fabric (asm-analysis)",
              "type": "Library",
              "artifact": {
                "size": 35151,
                "MD5": "3d63508405f5610fc2ea673ff5471553",
                "url": "https://github.com/mchdistro/byeol2ddan/raw/main/repo/lib/org/ow2/asm/asm-analysis/9.8/asm-analysis-9.8.jar"
              }
            },
            {
              "id": "org.ow2.asm:asm-commons:9.8",
              "name": "Fabric (asm-commons)",
              "type": "Library",
              "artifact": {
                "size": 73498,
                "MD5": "c8c3d9ccf240144e74d94ff658b024c9",
                "url": "https://github.com/mchdistro/byeol2ddan/raw/main/repo/lib/org/ow2/asm/asm-commons/9.8/asm-commons-9.8.jar"
              }
            },
            {
              "id": "org.ow2.asm:asm-tree:9.8",
              "name": "Fabric (asm-tree)",
              "type": "Library",
              "artifact": {
                "size": 51934,
                "MD5": "4ab1aaec43c77a2d9b56e6d6d496f705",
                "url": "https://github.com/mchdistro/byeol2ddan/raw/main/repo/lib/org/ow2/asm/asm-tree/9.8/asm-tree-9.8.jar"
              }
            },
            {
              "id": "org.ow2.asm:asm-util:9.8",
              "name": "Fabric (asm-util)",
              "type": "Library",
              "artifact": {
                "size": 94559,
                "MD5": "62498ef324bdab15f407d703f7d78d19",
                "url": "https://github.com/mchdistro/byeol2ddan/raw/main/repo/lib/org/ow2/asm/asm-util/9.8/asm-util-9.8.jar"
              }
            },
            {
              "id": "net.fabricmc:sponge-mixin:0.15.5+mixin.0.8.7",
              "name": "Fabric (sponge-mixin)",
              "type": "Library",
              "artifact": {
                "size": 1499194,
                "MD5": "f810932fdff9aa436d7d4f4ac69ce8c2",
                "url": "https://github.com/mchdistro/byeol2ddan/raw/main/repo/lib/net/fabricmc/sponge-mixin/0.15.5+mixin.0.8.7/sponge-mixin-0.15.5+mixin.0.8.7.jar"
              }
            },
            {
              "id": "net.fabricmc:intermediary:1.21.4",
              "name": "Fabric (intermediary)",
              "type": "Library",
              "artifact": {
                "size": 701826,
                "MD5": "d0f4187a62328d4a95f3428434efbd48",
                "url": "https://github.com/mchdistro/byeol2ddan/raw/main/repo/lib/net/fabricmc/intermediary/1.21.4/intermediary-1.21.4.jar"
              }
            }
          ]
        },
        {
          "id": "me.axieum.mcmod.authme.impl:authme:9.0.1+1.21.4@jar",
          "name": "Auth Me",
          "type": "FabricMod",
          "artifact": {
            "size": 376047,
            "url": "https://github.com/mchdistro/byeol2ddan/raw/main/servers/byeol2ddan-1.21.4/fabricmods/required/authme-fabric-9.0.1+1.21.4.jar",
            "MD5": "3c220399e5c34dae32224818c7acaa6c"
          }
        },
        {
          "id": "net.blay09.mods:balm:21.4.36@jar",
          "name": "Balm",
          "type": "FabricMod",
          "artifact": {
            "size": 605575,
            "url": "https://github.com/mchdistro/byeol2ddan/raw/main/servers/byeol2ddan-1.21.4/fabricmods/required/balm-fabric-1.21.4-21.4.36.jar",
            "MD5": "33618cde90ab3c36408fabb1c8651235"
          }
        },
        {
          "id": "kr.shihyeon:blurserveraddress:1.2.0+mc1.21.2@jar",
          "name": "BlurServerAddress",
          "type": "FabricMod",
          "artifact": {
            "size": 11418,
            "url": "https://github.com/mchdistro/byeol2ddan/raw/main/servers/byeol2ddan-1.21.4/fabricmods/required/blurserveraddress-fabric-1.2.0+mc1.21.2.jar",
            "MD5": "1294fe12bfc2d2dbe8e4541c27873fd2"
          }
        },
        {
          "id": "generated.fabricmod:cubes-without-borders:3.0.0+mc1.21.3@jar",
          "name": "Cubes Without Borders",
          "type": "FabricMod",
          "artifact": {
            "size": 80793,
            "url": "https://github.com/mchdistro/byeol2ddan/raw/main/servers/byeol2ddan-1.21.4/fabricmods/required/cwb-fabric-3.0.0+mc1.21.3.jar",
            "MD5": "4278e7e73cb1337e3a198f1c5b921887"
          }
        },
        {
          "id": "net.blay09.mods:defaultoptions:21.4.5@jar",
          "name": "Default Options",
          "type": "FabricMod",
          "artifact": {
            "size": 98192,
            "url": "https://github.com/mchdistro/byeol2ddan/raw/main/servers/byeol2ddan-1.21.4/fabricmods/required/defaultoptions-fabric-1.21.4-21.4.5.jar",
            "MD5": "e0b4098324c1d946864e5d3ade95046c"
          }
        },
        {
          "id": "generated.fabricmod:fabric-api:0.119.3+1.21.4@jar",
          "name": "Fabric API",
          "type": "FabricMod",
          "artifact": {
            "size": 2148367,
            "url": "https://github.com/mchdistro/byeol2ddan/raw/main/servers/byeol2ddan-1.21.4/fabricmods/required/fabric-api-0.119.3+1.21.4.jar",
            "MD5": "179994db46a00373614c47fb669d1dd3"
          }
        },
        {
          "id": "generated.fabricmod:ferritecore:7.1.1@jar",
          "name": "FerriteCore",
          "type": "FabricMod",
          "artifact": {
            "size": 107026,
            "url": "https://github.com/mchdistro/byeol2ddan/raw/main/servers/byeol2ddan-1.21.4/fabricmods/required/ferritecore-7.1.1-fabric.jar",
            "MD5": "cddea62080b823c0c55f72408a0c3ffb"
          }
        },
        {
          "id": "generated.fabricmod:immediatelyfast:1.8.1+1.21.4@jar",
          "name": "ImmediatelyFast",
          "type": "FabricMod",
          "artifact": {
            "size": 224739,
            "url": "https://github.com/mchdistro/byeol2ddan/raw/main/servers/byeol2ddan-1.21.4/fabricmods/required/ImmediatelyFast-Fabric-1.8.1+1.21.4.jar",
            "MD5": "5e7300090f35d5b3f54c6ebeb536e649"
          }
        },
        {
          "id": "generated.fabricmod:iris:1.8.8+mc1.21.4@jar",
          "name": "Iris",
          "type": "FabricMod",
          "artifact": {
            "size": 2682702,
            "url": "https://github.com/mchdistro/byeol2ddan/raw/main/servers/byeol2ddan-1.21.4/fabricmods/required/iris-fabric-1.8.8+mc1.21.4.jar",
            "MD5": "59d373e4874efbcb8fb426bdefa588d9"
          }
        },
        {
          "id": "generated.fabricmod:jei:1.21.4-neoforge-20.0.0.4@jar",
          "name": "Jei",
          "type": "FabricMod",
          "artifact": {
            "size": 1412277,
            "url": "https://github.com/mchdistro/byeol2ddan/raw/main/servers/byeol2ddan-1.21.4/fabricmods/required/jei-1.21.4-neoforge-20.0.0.4.jar",
            "MD5": "0a05755e844f8c0660929e81f2eae42e"
          }
        },
        {
          "id": "journeymap:journeymap:1.21.4-6.0.0-beta.47@jar",
          "name": "Journeymap",
          "type": "FabricMod",
          "artifact": {
            "size": 3514383,
            "url": "https://github.com/mchdistro/byeol2ddan/raw/main/servers/byeol2ddan-1.21.4/fabricmods/required/journeymap-fabric-1.21.4-6.0.0-beta.47.jar",
            "MD5": "8b092f8cca0a96d80eb8eeea24b5ebfd"
          }
        },
        {
          "id": "com.hyfata.najoan:koreanpatch:1.8.5+mc1.21.3@jar",
          "name": "Korean Patch",
          "type": "FabricMod",
          "artifact": {
            "size": 578977,
            "url": "https://github.com/mchdistro/byeol2ddan/raw/main/servers/byeol2ddan-1.21.4/fabricmods/required/koreanpatch-fabric-1.8.5+mc1.21.3.jar",
            "MD5": "fcf0f59c7f45c751af04527080bc4e28"
          }
        },
        {
          "id": "net.caffeinemc.mods:lithium:0.15.3+mc1.21.4@jar",
          "name": "Lithium",
          "type": "FabricMod",
          "artifact": {
            "size": 797555,
            "url": "https://github.com/mchdistro/byeol2ddan/raw/main/servers/byeol2ddan-1.21.4/fabricmods/required/lithium-fabric-0.15.3+mc1.21.4.jar",
            "MD5": "7a3a807eed9c4868fbe14cecd8bb082d"
          }
        },
        {
          "id": "com.aizistral:nochatreports:1.21.4-v2.11.0@jar",
          "name": "No Chat Reports",
          "type": "FabricMod",
          "artifact": {
            "size": 321286,
            "url": "https://github.com/mchdistro/byeol2ddan/raw/main/servers/byeol2ddan-1.21.4/fabricmods/required/NoChatReports-FABRIC-1.21.4-v2.11.0.jar",
            "MD5": "47bd3acbbaaf09dae1c5142dc5b3f41c"
          }
        },
        {
          "id": "su.plo.voice:plasmovoice:2.1.5@jar",
          "name": "Plasmo Voice",
          "type": "FabricMod",
          "artifact": {
            "size": 12191569,
            "url": "https://github.com/mchdistro/byeol2ddan/raw/main/servers/byeol2ddan-1.21.4/fabricmods/required/plasmovoice-fabric-1.21.4-2.1.5.jar",
            "MD5": "dde3cf502defa8513b1fb98afbc2dd11"
          }
        },
        {
          "id": "net.caffeinemc.mods:sodium:0.6.13+mc1.21.4@jar",
          "name": "Sodium",
          "type": "FabricMod",
          "artifact": {
            "size": 1306799,
            "url": "https://github.com/mchdistro/byeol2ddan/raw/main/servers/byeol2ddan-1.21.4/fabricmods/required/sodium-fabric-0.6.13+mc1.21.4.jar",
            "MD5": "28922a78d1876ee062e3265f10abcc46"
          }
        },
        {
          "id": "keybindings.txt",
          "name": "keybindings.txt",
          "type": "File",
          "artifact": {
            "size": 2874,
            "url": "https://github.com/mchdistro/byeol2ddan/raw/main/servers/byeol2ddan-1.21.4/files/config/defaultoptions/keybindings.txt",
            "MD5": "6dff6b8d3281a21378c7c85fcf195f56",
            "path": "config/defaultoptions/keybindings.txt"
          }
        },
        {
          "id": "options.txt",
          "name": "options.txt",
          "type": "File",
          "artifact": {
            "size": 2386,
            "url": "https://github.com/mchdistro/byeol2ddan/raw/main/servers/byeol2ddan-1.21.4/files/config/defaultoptions/options.txt",
            "MD5": "db5fe45d3f10471f383fbf83f210264f",
            "path": "config/defaultoptions/options.txt"
          }
        },
        {
          "id": "servers.dat",
          "name": "servers.dat",
          "type": "File",
          "artifact": {
            "size": 186,
            "url": "https://github.com/mchdistro/byeol2ddan/raw/main/servers/byeol2ddan-1.21.4/files/config/defaultoptions/servers.dat",
            "MD5": "cf1a99dc4bc094b3fb8752b8928177cb",
            "path": "config/defaultoptions/servers.dat"
          }
        }
      ]
    }
  ]
}